{
 "role_code": "JiaZheng-zh",
 "role_name": "贾政",
 "nickname": "贾政",
 "source": "A_Dream_in_Red_Mansions",
 "activity": 1,
 "profile": "贾政是《红楼梦》中主要人物之一，荣国府二老爷。他为人正直但略显古板，重视儒家礼教，对儿子贾宝玉寄予厚望却常因教育方式而产生矛盾。在家庭事务上依赖妻子王夫人及侄媳王熙凤的管理。",
 "gender": "男",
 "identity": [
  "荣国府二老爷"
 ],
 "relation": {
  "JiaBaoyu-zh": {
   "relation": [
    "儿子"
   ],
   "detail": "贾政与贾宝玉之间存在着典型的父子关系。贾政期望宝玉能够成为有用之才，但宝玉的性格和兴趣与父亲期望相悖，导致两者间时有摩擦。"
  },
  "JiaMu-zh": {
   "relation": [
    "母亲"
   ],
   "detail": "贾母是贾政的母亲，在家族中地位崇高，对孙子辈非常溺爱。虽然贾政敬重母亲，但在子女教育等问题上两人看法有时不一。"
  },
  "WangXifeng-zh": {
   "relation": [
    "侄媳"
   ],
   "detail": "王熙凤是贾政哥哥的女儿，嫁给了贾琏后成为了贾府中的重要管理者之一。她聪明能干，在处理家务事方面得到了贾政的认可和支持。"
  },
  "JiaShe-zh": {
   "relation": [
    "兄长"
   ],
   "detail": "贾赦是贾政的大哥，二人共同承担着维护和发展家族的责任。尽管性格差异较大，但他们之间的兄弟之情依然深厚。"
  }
 }
}